first_shell/__about__.py
first_shell/__init__.py
first_shell/__main__.py
first_shell/first_shell.tcss
first_shell/say.py
first_shell/xmas.py
first_shell-0.0.1.dist-info/METADATA
first_shell-0.0.1.dist-info/WHEEL
first_shell-0.0.1.dist-info/entry_points.txt
first_shell-0.0.1.dist-info/licenses/LICENSE.txt
first_shell-0.0.1.dist-info/RECORD
