Metadata-Version: 2.1
Name: first-shell
Version: 0.0.1
Summary: The first shell for every littel nerd
Project-URL: Documentation, https://github.com/unknown/first-shell#readme
Project-URL: Issues, https://github.com/unknown/first-shell/issues
Project-URL: Source, https://github.com/unknown/first-shell
Author-email: Frank Hoffmann <15r10nk-git@polarbit.de>
License-Expression: MIT
License-File: LICENSE.txt
Classifier: Development Status :: 4 - Beta
Classifier: Programming Language :: Python
Classifier: Programming Language :: Python :: 3.7
Classifier: Programming Language :: Python :: 3.8
Classifier: Programming Language :: Python :: 3.9
Classifier: Programming Language :: Python :: 3.10
Classifier: Programming Language :: Python :: 3.11
Classifier: Programming Language :: Python :: Implementation :: CPython
Classifier: Programming Language :: Python :: Implementation :: PyPy
Requires-Python: >=3.7
Requires-Dist: gtts>=2.4.0
Requires-Dist: pydub
Requires-Dist: simpleaudio
Requires-Dist: textual>=0.45.1
